lawyertools/__init__.py
lawyertools/app.py
lawyertools-0.0.1.data/scripts/lawyertools
lawyertools-0.0.1.dist-info/LICENSE
lawyertools-0.0.1.dist-info/METADATA
lawyertools-0.0.1.dist-info/WHEEL
lawyertools-0.0.1.dist-info/top_level.txt
lawyertools-0.0.1.dist-info/RECORD
